setup.py
teamspeaknotifier/__init__.py
teamspeaknotifier/notifier.py
teamspeaknotifier.egg-info/PKG-INFO
teamspeaknotifier.egg-info/SOURCES.txt
teamspeaknotifier.egg-info/dependency_links.txt
teamspeaknotifier.egg-info/entry_points.txt
teamspeaknotifier.egg-info/requires.txt
teamspeaknotifier.egg-info/top_level.txt