Metadata-Version: 1.0
Name: teamspeaknotifier
Version: 1.1.1
Summary: Show unobtrusive notifications when certain things happen in teamspeak.
Home-page: https://bitbucket.org/latestrevision/teamspeak-notification/
Author: Adam Coddington
Author-email: me@adamcoddington.net
License: UNKNOWN
Platform: UNKNOWN
Classifier: Intended Audience :: Developers
Classifier: License :: OSI Approved :: MIT License
Classifier: Programming Language :: Python
Classifier: Operating System :: POSIX :: Linux
Classifier: Topic :: Utilities
